labs/__init__.py
labs/cli.py
labs/cmake.py
labs/ninja.py
labs_build-0.1.dev0.dist-info/LICENSE.txt
labs_build-0.1.dev0.dist-info/METADATA
labs_build-0.1.dev0.dist-info/WHEEL
labs_build-0.1.dev0.dist-info/entry_points.txt
labs_build-0.1.dev0.dist-info/top_level.txt
labs_build-0.1.dev0.dist-info/RECORD
