Metadata-Version: 2.1
Name: labs-build
Version: 0.1.dev0
Summary: UNKNOWN
Home-page: https://github.com/hl037/labs
Author: Léo Flaventin Hauchecorne
Author-email: hl037.prog@gmail.com
License: GPLv3
Platform: UNKNOWN
Requires-Dist: addict (>=2.2.1)
Requires-Dist: click (>=0.7)
